sdamgia
