Metadata-Version: 2.1
Name: sdamgia-api
Version: 0.1.4
Summary: Python модуль для взаимодействия с образовательным порталом СДАМ ГИА
Home-page: https://github.com/anijackich/sdamgia-api
Author: anijack
Author-email: anijackich@gmail.com
License: MIT
Platform: UNKNOWN
Classifier: License :: OSI Approved :: MIT License
Classifier: Operating System :: OS Independent
Classifier: Programming Language :: Python :: 3
